iflow_mcp_bjornmelin_mcp_search_hub-0.1.0.dist-info/licenses/LICENSE
mcp_search_hub/__init__.py
mcp_search_hub/main.py
mcp_search_hub/server.py
iflow_mcp_bjornmelin_mcp_search_hub-0.1.0.dist-info/METADATA
iflow_mcp_bjornmelin_mcp_search_hub-0.1.0.dist-info/WHEEL
iflow_mcp_bjornmelin_mcp_search_hub-0.1.0.dist-info/entry_points.txt
iflow_mcp_bjornmelin_mcp_search_hub-0.1.0.dist-info/top_level.txt
iflow_mcp_bjornmelin_mcp_search_hub-0.1.0.dist-info/RECORD
