Metadata-Version: 2.4
Name: iflow-mcp_bjornmelin_mcp-search-hub
Version: 0.1.0
Summary: FastMCP 2.0 server integrating multiple search providers
Author: Bjorn Melin
Requires-Python: >=3.11
License-File: LICENSE
Requires-Dist: fastmcp>=2.3.5
Requires-Dist: pydantic>=2.11.4
Requires-Dist: httpx>=0.28.1
Requires-Dist: uvicorn>=0.34.2
Requires-Dist: python-dotenv>=1.1.0
Requires-Dist: mcp>=1.9.0
Requires-Dist: w3lib>=2.3.1
Requires-Dist: rapidfuzz>=3.13.0
Requires-Dist: scikit-learn>=1.6.1
Requires-Dist: numpy>=1.24.3
Requires-Dist: sentence-transformers>=4.1.0
Requires-Dist: torch>=2.0.0
Requires-Dist: dateparser>=1.2.1
Requires-Dist: redis>=6.1.0
Requires-Dist: pytest>=8.3.5
Requires-Dist: pytest-asyncio>=0.26.0
Requires-Dist: circuitbreaker>=2.1.3
Requires-Dist: pytest-cov>=6.1.1
Provides-Extra: dev
Requires-Dist: pytest>=8.0.0; extra == "dev"
Requires-Dist: pytest-asyncio>=0.24.0; extra == "dev"
Requires-Dist: pytest-cov>=5.0.0; extra == "dev"
Requires-Dist: ruff>=0.8.0; extra == "dev"
Provides-Extra: ml
Requires-Dist: diskcache>=5.6.3; extra == "ml"
Requires-Dist: onnx>=1.15.0; extra == "ml"
Requires-Dist: onnxruntime>=1.17.0; extra == "ml"
Requires-Dist: openvino>=2023.3.0; extra == "ml"
Dynamic: license-file
